django_salesforce-5.2.dist-info/licenses/AUTHORS.md
django_salesforce-5.2.dist-info/licenses/LICENSE.md
salesforce/__init__.py
salesforce/admin.py
salesforce/apps.py
salesforce/auth.py
salesforce/defaults.py
salesforce/fields.py
salesforce/models.py
salesforce/models_extend.py
salesforce/models_template.py
salesforce/router.py
salesforce/utils.py
salesforce/backend/__init__.py
salesforce/backend/base.py
salesforce/backend/client.py
salesforce/backend/compiler.py
salesforce/backend/creation.py
salesforce/backend/enterprise.py
salesforce/backend/features.py
salesforce/backend/indep.py
salesforce/backend/introspection.py
salesforce/backend/manager.py
salesforce/backend/models_lookups.py
salesforce/backend/models_sql_query.py
salesforce/backend/operations.py
salesforce/backend/query.py
salesforce/backend/schema.py
salesforce/backend/test_helpers.py
salesforce/backend/utils.py
salesforce/backend/validation.py
salesforce/dbapi/__init__.py
salesforce/dbapi/common.py
salesforce/dbapi/driver.py
salesforce/dbapi/exceptions.py
salesforce/dbapi/subselect.py
salesforce/dbapi/test_helpers.py
salesforce/management/__init__.py
salesforce/management/commands/__init__.py
salesforce/management/commands/inspectdb.py
salesforce/testrunner/__init__.py
salesforce/testrunner/local_settings.py.sample
salesforce/testrunner/settings.py
salesforce/testrunner/urls.py
salesforce/testrunner/example/__init__.py
salesforce/testrunner/example/admin.py
salesforce/testrunner/example/forms.py
salesforce/testrunner/example/models.py
salesforce/testrunner/example/models_template.py
salesforce/testrunner/example/tests.py
salesforce/testrunner/example/universal_admin.py
salesforce/testrunner/example/urls.py
salesforce/testrunner/example/views.py
salesforce/testrunner/example/templates/list-accounts.html
salesforce/testrunner/example/templates/search-accounts.html
salesforce/tests/__init__.py
salesforce/tests/test_auth.py
salesforce/tests/test_basic.py
salesforce/tests/test_browser.py
salesforce/tests/test_bulk.py
salesforce/tests/test_doc_tests.py
salesforce/tests/test_documents.py
django_salesforce-5.2.dist-info/METADATA
django_salesforce-5.2.dist-info/WHEEL
django_salesforce-5.2.dist-info/top_level.txt
django_salesforce-5.2.dist-info/RECORD
