Metadata-Version: 2.4
Name: django-salesforce
Version: 5.2
Summary: a Salesforce backend for Django's ORM
Author-email: Hynek Cernoch <hynek@sdb.cz>
Maintainer-email: Phil Christensen <phil@bubblehouse.org>
License: MIT (or AGPL)
Project-URL: Homepage, https://github.com/django-salesforce/django-salesforce
Project-URL: Funding, https://github.com/sponsors/hynekcer
Project-URL: Tracker, https://github.com/django-salesforce/django-salesforce/issues
Keywords: django,salesforce,orm,backend
Classifier: Development Status :: 5 - Production/Stable
Classifier: Intended Audience :: Developers
Classifier: Framework :: Django
Classifier: Programming Language :: Python
Requires-Python: >=3.8
License-File: LICENSE.md
License-File: AUTHORS.md
Requires-Dist: django<6.0,>=2.2
Requires-Dist: pytz>=2012c
Requires-Dist: requests>=2.32.0
Dynamic: license-file
Dynamic: requires-dist
